orekitfactory/__init__.py
orekitfactory/hooks.py
orekitfactory/initializer.py
orekitfactory/factory/__init__.py
orekitfactory/factory/conventions.py
orekitfactory/factory/dates.py
orekitfactory/factory/ellipsoids.py
orekitfactory/factory/frames.py
orekitfactory/factory/math.py
orekitfactory/factory/orbits.py
orekitfactory/factory/propagator.py
orekitfactory/time/__init__.py
orekitfactory/time/_dateinterval.py
orekitfactory/time/_dateintervallist.py
orekitfactory/utils/__init__.py
orekitfactory/utils/dataloader.py
orekitfactory/utils/quantity_units.py
orekitfactory/utils/urlvalidator.py
orekit_factory-0.2.0.dist-info/LICENSE
orekit_factory-0.2.0.dist-info/METADATA
orekit_factory-0.2.0.dist-info/WHEEL
orekit_factory-0.2.0.dist-info/entry_points.txt
orekit_factory-0.2.0.dist-info/top_level.txt
orekit_factory-0.2.0.dist-info/RECORD
